visuallm/__init__.py
visuallm/component_base.py
visuallm/named.py
visuallm/server.py
visuallm/components/__init__.py
visuallm/components/chat_component.py
visuallm/components/dataset_visualization_component.py
visuallm/components/generation_component.py
visuallm/components/next_token_prediction_component.py
visuallm/components/generators/__init__.py
visuallm/components/generators/base.py
visuallm/components/generators/huggingface.py
visuallm/components/generators/openai.py
visuallm/components/mixins/__init__.py
visuallm/components/mixins/data_preparation_mixin.py
visuallm/components/mixins/generation_selectors_mixin.py
visuallm/components/mixins/metrics_mixin.py
visuallm/components/mixins/model_selection_mixin.py
visuallm/dist/favicon.ico
visuallm/dist/index.html
visuallm/dist/assets/index-6a8b9578.css
visuallm/dist/assets/index-9b8c3d49.js
visuallm/elements/__init__.py
visuallm/elements/barchart_element.py
visuallm/elements/collapsible_element.py
visuallm/elements/element_base.py
visuallm/elements/plain_text_element.py
visuallm/elements/selector_elements.py
visuallm/elements/table_element.py
visuallm/elements/utils.py
visuallm/utils/sanitizer.py
visuallm-0.4.5.dist-info/LICENSE
visuallm-0.4.5.dist-info/METADATA
visuallm-0.4.5.dist-info/WHEEL
visuallm-0.4.5.dist-info/top_level.txt
visuallm-0.4.5.dist-info/RECORD
