Metadata-Version: 2.1
Name: visuallm
Version: 0.4.5
Summary: Visualization tool for various generation tasks on Language Models. 
Author-email: "Frantisek Trebuna (gortibaldik)" <ferotre@gmail.com>
Project-URL: Homepage, https://github.com/gortibaldik/visuallm
Project-URL: Bug Tracker, https://github.com/gortibaldik/visuallm/issues
Classifier: Programming Language :: Python :: 3
Classifier: License :: OSI Approved :: MIT License
Classifier: Operating System :: OS Independent
Requires-Python: >=3.10
License-File: LICENSE
Requires-Dist: Flask >=2.3.1
Requires-Dist: Flask-Cors >=3.0.10
Provides-Extra: huggingface
Requires-Dist: transformers ; extra == 'huggingface'
Requires-Dist: datasets ; extra == 'huggingface'
